PyMsOfa/PyMsOfa.py
PyMsOfa/PyMsOfa_astrometry.py
PyMsOfa/PyMsOfa_basic.py
PyMsOfa/PyMsOfa_earth_attitude.py
PyMsOfa/PyMsOfa_time.py
PyMsOfa/__init__.py
PyMsOfa_python-1.0.0.dist-info/LICENSE
PyMsOfa_python-1.0.0.dist-info/METADATA
PyMsOfa_python-1.0.0.dist-info/WHEEL
PyMsOfa_python-1.0.0.dist-info/top_level.txt
PyMsOfa_python-1.0.0.dist-info/RECORD
